pajAI/__init__.py
pajAI/ad_manager.py
pajAI-0.1.dist-info/LICENSE
pajAI-0.1.dist-info/METADATA
pajAI-0.1.dist-info/WHEEL
pajAI-0.1.dist-info/entry_points.txt
pajAI-0.1.dist-info/top_level.txt
pajAI-0.1.dist-info/RECORD
