Metadata-Version: 2.1
Name: pajAI
Version: 0.1
Summary: A package for managing Google Ad Manager tasks.
Home-page: https://github.com/yourusername/pajAI
Author: Pavle Bradic
Author-email: your_email@example.com
Classifier: Programming Language :: Python :: 3
Classifier: License :: OSI Approved :: MIT License
Classifier: Operating System :: OS Independent
Requires-Python: >=3.6
License-File: LICENSE
Requires-Dist: googleads
